tracking_fields/__init__.py
tracking_fields/admin.py
tracking_fields/decorators.py
tracking_fields/models.py
tracking_fields/settings.py
tracking_fields/tracking.py
tracking_fields/locale/fr/LC_MESSAGES/django.mo
tracking_fields/locale/fr/LC_MESSAGES/django.po
tracking_fields/migrations/0001_initial.py
tracking_fields/migrations/0002_auto_20160209_0356.py
tracking_fields/migrations/0003_auto_20220309_0347.py
tracking_fields/migrations/__init__.py
tracking_fields/templates/tracking_fields/admin/change_form_object.html
tracking_fields/templates/tracking_fields/admin/change_list_event.html
tracking_fields/templates/tracking_fields/admin/filter.html
tracking_fields/tests/__init__.py
tracking_fields/tests/admin.py
tracking_fields/tests/models.py
tracking_fields/tests/settings.py
tracking_fields/tests/tests.py
tracking_fields/tests/urls.py
django_tracking_fields-1.4.0.dist-info/LICENSE
django_tracking_fields-1.4.0.dist-info/METADATA
django_tracking_fields-1.4.0.dist-info/WHEEL
django_tracking_fields-1.4.0.dist-info/top_level.txt
django_tracking_fields-1.4.0.dist-info/RECORD
