Metadata-Version: 2.1
Name: django-tracking-fields
Version: 1.4.0
Summary: A Django app allowing the tracking of objects field in the admin site.
Home-page: https://github.com/makinacorpus/django-tracking-fields
Author: Yann Fouillat (alias Gagaro)
Author-email: yann.fouillat@makina-corpus.com
License: GPLv3+
Classifier: Environment :: Web Environment
Classifier: Framework :: Django
Classifier: Intended Audience :: Developers
Classifier: License :: OSI Approved :: GNU General Public License v3 or later (GPLv3+)
Classifier: Operating System :: OS Independent
Classifier: Programming Language :: Python
Classifier: Programming Language :: Python :: 3.5
Classifier: Programming Language :: Python :: 3.6
Classifier: Topic :: Internet :: WWW/HTTP
Classifier: Topic :: Internet :: WWW/HTTP :: Dynamic Content
License-File: LICENSE
